apache_bookkeeper_client-4.17.3.post1-py3.9-nspkg.pth
bookkeeper/types.py
bookkeeper/admin/__init__.py
bookkeeper/admin/client.py
bookkeeper/admin/exceptions.py
bookkeeper/admin/namespace.py
bookkeeper/admin/namespaces.py
bookkeeper/common/__init__.py
bookkeeper/common/constants.py
bookkeeper/common/datetime_helpers.py
bookkeeper/common/exceptions.py
bookkeeper/common/general_helpers.py
bookkeeper/common/grpc_helpers.py
bookkeeper/common/method.py
bookkeeper/common/protobuf_helpers.py
bookkeeper/common/retry.py
bookkeeper/common/service_uri.py
bookkeeper/common/timeout.py
bookkeeper/common/util.py
bookkeeper/common/future/__init__.py
bookkeeper/common/future/_helpers.py
bookkeeper/common/future/base.py
bookkeeper/common/future/polling.py
bookkeeper/common/router/__init__.py
bookkeeper/common/router/router.py
bookkeeper/kv/__init__.py
bookkeeper/kv/client.py
bookkeeper/kv/exceptions.py
bookkeeper/kv/futures.py
bookkeeper/kv/table.py
bookkeeper/proto/__init__.py
bookkeeper/proto/cluster_pb2.py
bookkeeper/proto/common_pb2.py
bookkeeper/proto/kv_pb2.py
bookkeeper/proto/kv_rpc_pb2.py
bookkeeper/proto/kv_rpc_pb2_grpc.py
bookkeeper/proto/kv_store_pb2.py
bookkeeper/proto/storage_pb2.py
bookkeeper/proto/storage_pb2_grpc.py
bookkeeper/proto/stream_pb2.py
apache_bookkeeper_client-4.17.3.post1.dist-info/METADATA
apache_bookkeeper_client-4.17.3.post1.dist-info/WHEEL
apache_bookkeeper_client-4.17.3.post1.dist-info/namespace_packages.txt
apache_bookkeeper_client-4.17.3.post1.dist-info/top_level.txt
apache_bookkeeper_client-4.17.3.post1.dist-info/RECORD
